sandevistan/__init__.py
sandevistan/_version.py
sandevistan/analyzer.py
sandevistan/cli.py
sandevistan/config.py
sandevistan/scraper.py
sandevistan-0.3.0.dist-info/licenses/LICENSE
sandevistan-0.3.0.dist-info/METADATA
sandevistan-0.3.0.dist-info/WHEEL
sandevistan-0.3.0.dist-info/entry_points.txt
sandevistan-0.3.0.dist-info/top_level.txt
sandevistan-0.3.0.dist-info/RECORD
