Metadata-Version: 2.4
Name: sandevistan
Version: 0.3.0
Summary: AI-powered CLI tool to analyze Apple crash files
Author: Dil4rd
License-Expression: MIT
Project-URL: Homepage, https://github.com/Dil4rd/sandevistan
Project-URL: Repository, https://github.com/Dil4rd/sandevistan
Project-URL: Issues, https://github.com/Dil4rd/sandevistan/issues
Keywords: crash,analysis,apple,ios,macos,ai,gemini,langgraph
Classifier: Development Status :: 3 - Alpha
Classifier: Intended Audience :: Developers
Classifier: Operating System :: OS Independent
Classifier: Programming Language :: Python :: 3
Classifier: Programming Language :: Python :: 3.11
Classifier: Programming Language :: Python :: 3.12
Classifier: Topic :: Software Development :: Debuggers
Classifier: Topic :: System :: Logging
Requires-Python: >=3.11
License-File: LICENSE
Requires-Dist: langgraph>=0.2.0
Requires-Dist: google-genai>=0.1.0
Requires-Dist: click>=8.0.0
Requires-Dist: tomli-w>=1.0.0
Requires-Dist: beautifulsoup4>=4.12.0
Requires-Dist: requests>=2.31.0
Dynamic: license-file
